{
  "meta": {
    "generated_at": "2026-05-19T12:42:06.631229",
    "generated_date": "2026-05-19",
    "generated_time": "12:42 IST",
    "data_source": "Upstox API v2",
    "index_lookback_days": 365,
    "breadth_lookback_days": 50,
    "schema_version": "1.5",
    "data_as_of": "2026-05-18",
    "data_as_of_label": "Mon 18 May 2026 close",
    "is_intraday_partial": false,
    "is_stale": false,
    "data_freshness": "fresh",
    "data_status_text": "✓ EOD final"
  },
  "market_pulse": {
    "nifty": {
      "current_close": 23649.95,
      "prev_close": 23643.5,
      "change_pct": 0.03,
      "ema_20": 23857.33,
      "ema_50": 24064.08,
      "ema_200": 24737.41,
      "atr_14": 339.8,
      "high_52w": 26373.2,
      "low_52w": 22182.55,
      "candle_count": 248,
      "label": "Nifty 50",
      "instrument_key": "NSE_INDEX|Nifty 50"
    },
    "bank_nifty": {
      "current_close": 53537.0,
      "prev_close": 53710.35,
      "change_pct": -0.32,
      "ema_20": 54718.18,
      "ema_50": 55553.34,
      "ema_200": 56447.99,
      "atr_14": 997.54,
      "high_52w": 61764.85,
      "low_52w": 49954.85,
      "candle_count": 248,
      "label": "Bank Nifty",
      "instrument_key": "NSE_INDEX|Nifty Bank"
    },
    "midcap": {
      "current_close": 17261.35,
      "prev_close": 17273.15,
      "change_pct": -0.07,
      "ema_20": 17071.97,
      "ema_50": 16765.54,
      "ema_200": 16608.18,
      "atr_14": 280.77,
      "high_52w": 17686.3,
      "low_52w": 14804.55,
      "candle_count": 248,
      "label": "Nifty Midcap 50",
      "instrument_key": "NSE_INDEX|Nifty Midcap 50"
    },
    "vix": {
      "current_close": 19.63,
      "prev_close": 18.79,
      "change_pct": 4.47,
      "ema_20": 18.76,
      "ema_50": 18.61,
      "ema_200": 15.27,
      "atr_14": 1.9,
      "high_52w": 28.91,
      "low_52w": 8.72,
      "candle_count": 248,
      "label": "India VIX",
      "instrument_key": "NSE_INDEX|India VIX"
    }
  },
  "market_regime": {
    "regime": "Correcting",
    "active_modules": [
      "M2"
    ],
    "description": "Nifty below 20 & 50 EMA. Breadth 38% (Nifty 500)",
    "colour": "orange"
  },
  "regime_transition": {
    "history": [
      {
        "date": "2026-05-13",
        "regime": "Correcting",
        "label": "CORR",
        "colour": "correct"
      },
      {
        "date": "2026-05-14",
        "regime": "Correcting",
        "label": "CORR",
        "colour": "correct"
      },
      {
        "date": "2026-05-15",
        "regime": "Correcting",
        "label": "CORR",
        "colour": "correct"
      },
      {
        "date": "2026-05-18",
        "regime": "Correcting",
        "label": "CORR",
        "colour": "correct"
      },
      {
        "date": "2026-05-19",
        "regime": "Correcting",
        "label": "CORR",
        "colour": "correct"
      }
    ],
    "status": "STABLE CORR",
    "days_in_regime": 5,
    "direction": "stable",
    "note": "Trend intact — normal sizing"
  },
  "breadth": {
    "breadth_pct": 37.8,
    "above_ema": 189,
    "below_ema": 311,
    "errors": 0,
    "total_constituents": 500,
    "total_computed": 500,
    "index_used": "NIFTY 500",
    "breadth_3d_ago": 48.8,
    "change_3d": -11.0
  },
  "market_insight": [
    {
      "severity": "high",
      "trigger": "breadth_contraction",
      "text": "Breadth 49% → 38% in 3 days — narrow leadership, tighten"
    }
  ],
  "insight_fallback_text": "Correction intact for 5 sessions.",
  "playbook": {
    "run": [
      {
        "module": "M2",
        "priority": "primary",
        "name": "Oversold Bounce"
      }
    ],
    "skip": [
      {
        "module": "M1",
        "name": "Trend Pullback"
      },
      {
        "module": "M3",
        "name": "Range Breakout"
      }
    ],
    "cap_new_entries": 2,
    "size_rule": "full",
    "size_reason": "",
    "override": null,
    "today_mode": {
      "mode": "M2 ONLY — half size",
      "wait_for": "Deep oversold bounces in strong names",
      "dont": "M1 or M3 in this regime"
    }
  },
  "scan_here": {
    "ready": [
      {
        "sector": "FMCG",
        "distance_pct": 0.64
      },
      {
        "sector": "METAL",
        "distance_pct": 1.64
      }
    ],
    "extended": [
      {
        "sector": "PHARMA",
        "distance_pct": 4.45
      }
    ],
    "weak": [
      {
        "sector": "CONSUMER_DURABLES",
        "distance_pct": -3.69
      },
      {
        "sector": "REALTY",
        "distance_pct": -3.43
      },
      {
        "sector": "OIL_GAS",
        "distance_pct": -2.26
      },
      {
        "sector": "IT",
        "distance_pct": -2.18
      },
      {
        "sector": "BANK",
        "distance_pct": -2.16
      },
      {
        "sector": "AUTO",
        "distance_pct": -2.04
      },
      {
        "sector": "FIN_SERVICES",
        "distance_pct": -1.4
      }
    ],
    "ready_threshold_pct": 3.0
  },
  "watchlist": {
    "m1": [
      {
        "symbol": "DABUR",
        "sector": "FMCG",
        "close": 456.35,
        "metric_label": "dist from 20EMA",
        "metric_value": "+0.0%"
      },
      {
        "symbol": "HINDUNILVR",
        "sector": "FMCG",
        "close": 2254.2,
        "metric_label": "dist from 20EMA",
        "metric_value": "+0.0%"
      },
      {
        "symbol": "LLOYDSME",
        "sector": "METAL",
        "close": 1697.1,
        "metric_label": "dist from 20EMA",
        "metric_value": "+0.7%"
      },
      {
        "symbol": "ITC",
        "sector": "FMCG",
        "close": 310.15,
        "metric_label": "dist from 20EMA",
        "metric_value": "+1.3%"
      },
      {
        "symbol": "HINDALCO",
        "sector": "METAL",
        "close": 1053.1,
        "metric_label": "dist from 20EMA",
        "metric_value": "+1.3%"
      }
    ],
    "m3": [
      {
        "symbol": "ITC",
        "sector": "FMCG",
        "close": 310.15,
        "metric_label": "20d range",
        "metric_value": "5.9%"
      },
      {
        "symbol": "JSWSTEEL",
        "sector": "METAL",
        "close": 1292.8,
        "metric_label": "20d range",
        "metric_value": "6.6%"
      },
      {
        "symbol": "COLPAL",
        "sector": "FMCG",
        "close": 2151.2,
        "metric_label": "20d range",
        "metric_value": "7.2%"
      },
      {
        "symbol": "PATANJALI",
        "sector": "FMCG",
        "close": 456.75,
        "metric_label": "20d range",
        "metric_value": "8.6%"
      },
      {
        "symbol": "JINDALSTEL",
        "sector": "METAL",
        "close": 1231.8,
        "metric_label": "20d range",
        "metric_value": "8.8%"
      }
    ],
    "m2": [],
    "m2_active": true,
    "total_ranked": 10,
    "universe_note": null
  },
  "sector_regimes": {
    "BANK": {
      "current_close": 53537.0,
      "prev_close": 53710.35,
      "change_pct": -0.32,
      "ema_20": 54718.18,
      "ema_50": 55553.34,
      "ema_200": 56447.99,
      "atr_14": 997.54,
      "high_52w": 61764.85,
      "low_52w": 49954.85,
      "candle_count": 248,
      "label": "Nifty Bank",
      "instrument_key": "NSE_INDEX|Nifty Bank",
      "regime": "Correcting",
      "position_size_rule": "Skip trade entirely",
      "regime_colour": "correct"
    },
    "IT": {
      "current_close": 28389.8,
      "prev_close": 27716.9,
      "change_pct": 2.43,
      "ema_20": 29023.55,
      "ema_50": 30272.33,
      "ema_200": 33895.8,
      "atr_14": 702.85,
      "high_52w": 40301.4,
      "low_52w": 27078.0,
      "candle_count": 248,
      "label": "Nifty IT",
      "instrument_key": "NSE_INDEX|Nifty IT",
      "regime": "Correcting",
      "position_size_rule": "Skip trade entirely",
      "regime_colour": "correct"
    },
    "FIN_SERVICES": {
      "current_close": 25349.75,
      "prev_close": 25343.85,
      "change_pct": 0.02,
      "ema_20": 25710.35,
      "ema_50": 25993.34,
      "ema_200": 26507.82,
      "atr_14": 456.56,
      "high_52w": 28562.5,
      "low_52w": 23373.95,
      "candle_count": 248,
      "label": "Nifty Fin Services",
      "instrument_key": "NSE_INDEX|Nifty Fin Service",
      "regime": "Sideways",
      "position_size_rule": "50% of calculated size",
      "regime_colour": "side"
    },
    "AUTO": {
      "current_close": 25624.3,
      "prev_close": 26070.7,
      "change_pct": -1.71,
      "ema_20": 26156.64,
      "ema_50": 26198.62,
      "ema_200": 25976.78,
      "atr_14": 576.2,
      "high_52w": 29179.1,
      "low_52w": 22915.65,
      "candle_count": 248,
      "label": "Nifty Auto",
      "instrument_key": "NSE_INDEX|Nifty Auto",
      "regime": "Correcting",
      "position_size_rule": "Skip trade entirely",
      "regime_colour": "correct"
    },
    "FMCG": {
      "current_close": 50900.1,
      "prev_close": 51051.35,
      "change_pct": -0.3,
      "ema_20": 50577.05,
      "ema_50": 50176.84,
      "ema_200": 52660.94,
      "atr_14": 741.8,
      "high_52w": 58485.05,
      "low_52w": 45334.15,
      "candle_count": 248,
      "label": "Nifty FMCG",
      "instrument_key": "NSE_INDEX|Nifty FMCG",
      "regime": "Bullish",
      "position_size_rule": "100% of calculated size",
      "regime_colour": "side"
    },
    "METAL": {
      "current_close": 13169.95,
      "prev_close": 13300.6,
      "change_pct": -0.98,
      "ema_20": 12957.95,
      "ema_50": 12481.99,
      "ema_200": 11061.65,
      "atr_14": 257.8,
      "high_52w": 13628.65,
      "low_52w": 8997.35,
      "candle_count": 248,
      "label": "Nifty Metal",
      "instrument_key": "NSE_INDEX|Nifty Metal",
      "regime": "Bullish",
      "position_size_rule": "100% of calculated size",
      "regime_colour": "side"
    },
    "PHARMA": {
      "current_close": 24762.85,
      "prev_close": 24634.8,
      "change_pct": 0.52,
      "ema_20": 23708.19,
      "ema_50": 23122.94,
      "ema_200": 22522.76,
      "atr_14": 382.69,
      "high_52w": 24847.9,
      "low_52w": 21149.9,
      "candle_count": 248,
      "label": "Nifty Pharma",
      "instrument_key": "NSE_INDEX|Nifty Pharma",
      "regime": "Bullish",
      "position_size_rule": "100% of calculated size",
      "regime_colour": "side"
    },
    "REALTY": {
      "current_close": 751.95,
      "prev_close": 756.3,
      "change_pct": -0.58,
      "ema_20": 778.65,
      "ema_50": 774.8,
      "ema_200": 847.64,
      "atr_14": 21.58,
      "high_52w": 1049.7,
      "low_52w": 638.65,
      "candle_count": 248,
      "label": "Nifty Realty",
      "instrument_key": "NSE_INDEX|Nifty Realty",
      "regime": "Correcting",
      "position_size_rule": "Skip trade entirely",
      "regime_colour": "correct"
    },
    "OIL_GAS": {
      "current_close": 11162.5,
      "prev_close": 11250.7,
      "change_pct": -0.78,
      "ema_20": 11420.91,
      "ema_50": 11446.75,
      "ema_200": 11518.42,
      "atr_14": 194.56,
      "high_52w": 12445.7,
      "low_52w": 10580.95,
      "candle_count": 248,
      "label": "Nifty Oil & Gas",
      "instrument_key": "NSE_INDEX|NIFTY OIL AND GAS",
      "regime": "Correcting",
      "position_size_rule": "Skip trade entirely",
      "regime_colour": "correct"
    },
    "CONSUMER_DURABLES": {
      "current_close": 34916.75,
      "prev_close": 35555.6,
      "change_pct": -1.8,
      "ema_20": 36255.32,
      "ema_50": 36315.22,
      "ema_200": 37108.92,
      "atr_14": 882.19,
      "high_52w": 40472.45,
      "low_52w": 32587.95,
      "candle_count": 248,
      "label": "Nifty Consumer Durables",
      "instrument_key": "NSE_INDEX|NIFTY CONSR DURBL",
      "regime": "Correcting",
      "position_size_rule": "Skip trade entirely",
      "regime_colour": "correct"
    }
  },
  "modules": {
    "M1": {
      "name": "Trend Pullback",
      "active_in": [
        "Bullish Trending"
      ],
      "entry": "Strong stock in uptrend pulling back to 20 EMA. Entry on bullish candle bounce.",
      "stop": "Entry - (1.5 x ATR14)",
      "target": "2.5x risk distance",
      "hold": "5-15 days"
    },
    "M2": {
      "name": "Oversold Bounce",
      "active_in": [
        "Correcting",
        "Recovering"
      ],
      "entry": "Quality stock above 200 EMA, RSI < 38, down 8%+ in 5 days. First green candle (body > 50%).",
      "stop": "Entry - (1.5 x ATR14)",
      "target": "5-8% or prior resistance",
      "hold": "2-7 days"
    },
    "M3": {
      "name": "Range Breakout",
      "active_in": [
        "Bullish Trending",
        "Sideways",
        "Recovering"
      ],
      "entry": "8-12% range for 15-30 sessions, volume drying up. Close above range high, vol >= 2x 20d avg.",
      "stop": "Entry - (1.5 x ATR14)",
      "target": "3x risk distance",
      "hold": "5-21 days"
    }
  },
  "risk_rules": {
    "max_risk_per_trade": "0.5% of capital",
    "max_open_trades": 5,
    "max_portfolio_risk": "2.5% of capital",
    "stop_loss_method": "Entry - (1.5 x ATR14)",
    "time_stop": "Exit if no movement in 10 sessions",
    "loss_streak_rule": "3 consecutive losses in a week -> stop that week",
    "monthly_drawdown": "Down 5% -> reduce sizes by 50% next month"
  }
}