[
  {
    "date": "2026-06-11",
    "regime": "Correcting"
  },
  {
    "date": "2026-06-12",
    "regime": "Correcting"
  },
  {
    "date": "2026-06-15",
    "regime": "Sideways"
  },
  {
    "date": "2026-06-16",
    "regime": "Bullish Trending"
  },
  {
    "date": "2026-06-17",
    "regime": "Bullish Trending"
  },
  {
    "date": "2026-06-18",
    "regime": "Bullish Trending"
  },
  {
    "date": "2026-06-19",
    "regime": "Bullish Trending"
  },
  {
    "date": "2026-06-22",
    "regime": "Bullish Trending"
  },
  {
    "date": "2026-06-23",
    "regime": "Bullish Trending"
  },
  {
    "date": "2026-06-24",
    "regime": "Sideways"
  },
  {
    "date": "2026-06-25",
    "regime": "Bullish Trending"
  },
  {
    "date": "2026-06-26",
    "regime": "Bullish Trending"
  },
  {
    "date": "2026-06-29",
    "regime": "Bullish Trending"
  },
  {
    "date": "2026-06-30",
    "regime": "Sideways"
  },
  {
    "date": "2026-07-01",
    "regime": "Sideways"
  },
  {
    "date": "2026-07-02",
    "regime": "Bullish Trending"
  },
  {
    "date": "2026-07-03",
    "regime": "Bullish Trending"
  },
  {
    "date": "2026-07-06",
    "regime": "Bullish Trending"
  },
  {
    "date": "2026-07-07",
    "regime": "Bullish Trending"
  },
  {
    "date": "2026-07-08",
    "regime": "Bullish Trending"
  }
]